nonebot_plugin_easy_blacklist/__init__.py
nonebot_plugin_easy_blacklist/api.py
nonebot_plugin_easy_blacklist/config.py
nonebot_plugin_easy_blacklist/core.py
nonebot_plugin_easy_blacklist/load_data.py
nonebot_plugin_easy_blacklist/run_state.py
nonebot_plugin_easy_blacklist/schedule.py
nonebot_plugin_easy_blacklist-1.5.dist-info/METADATA
nonebot_plugin_easy_blacklist-1.5.dist-info/WHEEL
nonebot_plugin_easy_blacklist-1.5.dist-info/top_level.txt
nonebot_plugin_easy_blacklist-1.5.dist-info/RECORD
