Metadata-Version: 2.1
Name: nonebot-plugin-easy-blacklist
Version: 1.5
Summary: 一个轻量级的黑名单插件,支持api接入全平台,内存占用优化中
Home-page: https://github.com/bingqiu456/nonebot-plugin-easy-blacklist
Author: bingyue
Author-email: hello-yiqiu@qq.com
Keywords: nonebot_plugin_easy_blacklist,easy_blacklist,blacklist
Requires-Dist: aiofiles >=0.8.0
Requires-Dist: nonebot2 >=2.1.3
Requires-Dist: nonebot-adapter-onebot >=2.1.3
Requires-Dist: nonebot-plugin-apscheduler >=0.3.0
